{
  "fecha": "2025-08-16",
  "tecnologia": "css",
  "nombre_tema": "CSS Grid Layout: Grid Template Areas",
  "explicacion_tema": "El atributo grid-template-areas permite definir un layout de grid mediante áreas etiquetadas. Permite crear layouts complejos y personalizados con facilidad, definiendo áreas específicas para cada elemento del grid. Se utiliza combinado con el atributo grid-template-columns y grid-template-rows para crear un layout completo.",
  "generadoEn": "2025-08-16T08:25:05.410Z"
}